DBOpt/DBOpt.py
DBOpt/DBOpt_utility.py
DBOpt/DB_optimize.py
DBOpt/__init__.py
DBOpt/auto_plot.py
DBOpt/bounds_utility.py
DBOpt/cluster_plots.py
DBOpt/countour_plots.py
DBOpt/optimize.py
DBOpt/output_utility.py
DBOpt/parallel_plots.py
DBOpt/single_dim_plots.py
DBOpt-1.0.0.dist-info/LICENSE
DBOpt-1.0.0.dist-info/METADATA
DBOpt-1.0.0.dist-info/WHEEL
DBOpt-1.0.0.dist-info/top_level.txt
DBOpt-1.0.0.dist-info/RECORD
