Metadata-Version: 2.1
Name: DBOpt
Version: 1.0.0
Summary: Bayesian optimized parameter selection for density-based clustering algorithms
Home-page: https://github.com/Kaufman-Lab-Columbia/DBOpt
Author: Joseph L. Hammer, Alexander J. Devanny
Author-email: jhammer3018@gmail.com
License: MIT
Keywords: cluster clusters clustering DBSCAN HDBSCAN OPTICS
Classifier: License :: OSI Approved :: MIT License
Classifier: Programming Language :: Python :: 3
Classifier: Topic :: Scientific/Engineering
License-File: LICENSE
Requires-Dist: kDBCV==1.0.0
Requires-Dist: bayesian-optimization==1.5.1
Requires-Dist: numpy<2,>=1.20.0
Requires-Dist: scikit-learn>=1.3
